pipenv2deb/__init__.py
pipenv2deb/__main__.py
pipenv2deb-2.0.7.data/scripts/pipenv2deb
pipenv2deb-2.0.7.dist-info/LICENSE
pipenv2deb-2.0.7.dist-info/METADATA
pipenv2deb-2.0.7.dist-info/WHEEL
pipenv2deb-2.0.7.dist-info/top_level.txt
pipenv2deb-2.0.7.dist-info/RECORD
