Metadata-Version: 2.1
Name: pipenv2deb
Version: 2.0.7
Summary: A tool to produce a deb installer for a python projects that use pipenv.
Home-page: https://github.com/pjaos/pipenv2deb
Author: Paul Austen
Author-email: pausten.os@gmail.com
License: UNKNOWN
Platform: UNKNOWN
Classifier: Programming Language :: Python :: 3
Classifier: License :: OSI Approved :: MIT License
Classifier: Operating System :: OS Independent
License-File: LICENSE
